slactrac/__init__.py
slactrac/baseclass.py
slactrac/beamline.py
slactrac/BeamParams.py
slactrac/bend.py
slactrac/bunchgen.py
slactrac/classes.py
slactrac/conversions.py
slactrac/driftmat.py
slactrac/elegant_sim.py
slactrac/focusmat.py
slactrac/quadmat.py
slactrac/scatter.py
slactrac/Twiss.py
SLACtrac-1.0.2.dist-info/DESCRIPTION.rst
SLACtrac-1.0.2.dist-info/METADATA
SLACtrac-1.0.2.dist-info/metadata.json
SLACtrac-1.0.2.dist-info/RECORD
SLACtrac-1.0.2.dist-info/top_level.txt
SLACtrac-1.0.2.dist-info/WHEEL
